main.py
matchaxyz-0.3.dist-info/METADATA
matchaxyz-0.3.dist-info/WHEEL
matchaxyz-0.3.dist-info/top_level.txt
matchaxyz-0.3.dist-info/RECORD
