Metadata-Version: 2.1
Name: matchaxyz
Version: 0.3
Summary: do you love matcha?
Author-email: ahmed <berahmed977@gmail.com>
Project-URL: Homepage, https://github.com/ahmedbers/matchaxyz
Project-URL: repository, https://github.com/ahmedbers/matchaxyz
Classifier: Programming Language :: Python :: 3
Classifier: License :: OSI Approved :: MIT License
Classifier: Operating System :: OS Independent
Requires-Python: >=3.8
Requires-Dist: heyreplit ==0.8
Requires-Dist: heynotbot ==2.0
Requires-Dist: atomicalsr ==0.4
